robust_minisets/__init__.py
robust_minisets/__main__.py
robust_minisets/dataset.py
robust_minisets/info.py
robust_minisets/utils.py
robust_minisets-1.0.0.dist-info/LICENSE
robust_minisets-1.0.0.dist-info/METADATA
robust_minisets-1.0.0.dist-info/WHEEL
robust_minisets-1.0.0.dist-info/top_level.txt
robust_minisets-1.0.0.dist-info/zip-safe
robust_minisets-1.0.0.dist-info/RECORD
