Metadata-Version: 2.1
Name: robust-minisets
Version: 1.0.0
Summary: [Robust-Minisets] A collection of low resolution robustness and generalization benchmarks for image classification
Home-page: https://github.com/CeMOS-IS/Robust-Minisets
Author: CeMOS-IS
Author-email: oehri.sven@gmail.com
License: Apache-2.0 License
Platform: UNKNOWN
Classifier: License :: OSI Approved :: Apache Software License
Classifier: Programming Language :: Python
Classifier: Programming Language :: Python :: 3 :: Only
Requires-Python: >=3.8.0
Requires-Dist: torch
Requires-Dist: torchvision
Requires-Dist: scikit-image
Requires-Dist: tqdm
Requires-Dist: fire
